Metadata-Version: 1.0
Name: nasz-projekt
Version: 1.1
Summary: Opis
Home-page: http://jsystems.pl
Author: Marcin
Author-email: m.bazydlo@jsystems.pl
License: UNKNOWN
Platform: UNKNOWN
